sis_calibration/Mixer.py
sis_calibration/__init__.py
sis_calibration/if_impedance.py
sis_calibration/logger.py
sis_calibration/respfn.py
sis_calibration/utils.py
sis_calibration/impedances/__init__.py
sis_calibration/impedances/impedances.py
sis_calibration-0.28.dist-info/METADATA
sis_calibration-0.28.dist-info/WHEEL
sis_calibration-0.28.dist-info/top_level.txt
sis_calibration-0.28.dist-info/RECORD
