Metadata-Version: 2.1
Name: sis-calibration
Version: 0.28
Summary: SIS calibration
Home-page: https://github.com/sisteralab/sis-calibration
Author: sisteralab
Author-email: ya.vodzyanovskiy@lebedev.ru
Keywords: sis vna
Requires-Dist: numpy
Requires-Dist: scipy
Requires-Dist: mpmath
Requires-Dist: matplotlib
Requires-Dist: port-calibration
